vdb/__init__.py
vdb/cli.py
vdb/lib/__init__.py
vdb/lib/aqua.py
vdb/lib/cna.py
vdb/lib/config.py
vdb/lib/cve.py
vdb/lib/db6.py
vdb/lib/display.py
vdb/lib/gha.py
vdb/lib/npm.py
vdb/lib/nvd.py
vdb/lib/orasclient.py
vdb/lib/osv.py
vdb/lib/search.py
vdb/lib/utils.py
vdb/lib/cve_model/__init__.py
vdb/lib/cve_model/common.py
vdb/lib/cve_model/cvss_v2.py
vdb/lib/cve_model/cvss_v3.py
vdb/lib/cve_model/cvss_v4.py
vdb/lib/cve_model/tagger.py
appthreat_vulnerability_db-6.5.1.dist-info/METADATA
appthreat_vulnerability_db-6.5.1.dist-info/WHEEL
appthreat_vulnerability_db-6.5.1.dist-info/entry_points.txt
appthreat_vulnerability_db-6.5.1.dist-info/top_level.txt
appthreat_vulnerability_db-6.5.1.dist-info/RECORD
