Metadata-Version: 2.4
Name: appthreat-vulnerability-db
Version: 6.5.1
Summary: AppThreat's vulnerability database and package search library with a built-in sqlite based storage. OSV, CVE, GitHub, npm are the primary sources of vulnerabilities.
Author-email: Team AppThreat <cloud@appthreat.com>
License: MIT
Project-URL: Homepage, https://github.com/appthreat/vulnerability-db
Classifier: Development Status :: 5 - Production/Stable
Classifier: Intended Audience :: Developers
Classifier: Intended Audience :: System Administrators
Classifier: License :: OSI Approved :: MIT License
Classifier: Operating System :: OS Independent
Classifier: Programming Language :: Python :: 3.14
Classifier: Programming Language :: Python :: 3.13
Classifier: Programming Language :: Python :: 3.12
Classifier: Programming Language :: Python :: 3.11
Classifier: Programming Language :: Python :: 3.10
Classifier: Programming Language :: Python :: Free Threading :: 1 - Unstable
Classifier: Topic :: Security
Classifier: Topic :: Utilities
Requires-Python: >=3.10
Requires-Dist: httpx[http2]
Requires-Dist: appdirs
Requires-Dist: orjson
Requires-Dist: semver
Requires-Dist: packageurl-python
Requires-Dist: cvss
Requires-Dist: pydantic[email]
Requires-Dist: rich
Requires-Dist: apsw
Provides-Extra: dev
Requires-Dist: black; extra == "dev"
Requires-Dist: bandit; extra == "dev"
Requires-Dist: flake8; extra == "dev"
Requires-Dist: pylint; extra == "dev"
Requires-Dist: pytest; extra == "dev"
Requires-Dist: pytest-cov; extra == "dev"
Provides-Extra: oras
Requires-Dist: oras>=0.2.25; extra == "oras"
Provides-Extra: all
Requires-Dist: oras>=0.2.25; extra == "all"
